{"chanID":"-1001059262199","lastUpdated":"2016-08-16T05:00:12+02:00","total":[{"playerID":"101700363","name":"Nilam Atsirina K","score":343,"position":1},{"playerID":"241554335","name":"Inar Wardhani","score":278,"position":2},{"playerID":"269198777","name":"Danil Oktriyo","score":151,"position":3},{"playerID":"265804542","name":"Arlingga Tirta","score":150,"position":4}],"rank":{"2016-32":[{"playerID":"101700363","name":"Nilam Atsirina K","score":343,"position":1},{"playerID":"241554335","name":"Inar Wardhani","score":230,"position":2},{"playerID":"269198777","name":"Danil Oktriyo","score":122,"position":3}],"2016-33":[{"playerID":"265804542","name":"Arlingga Tirta","score":150,"position":1},{"playerID":"241554335","name":"Inar Wardhani","score":48,"position":2},{"playerID":"269198777","name":"Danil Oktriyo","score":29,"position":3}]}}
