{"chanID":"-117684103","lastUpdated":"2016-10-07T05:02:27+02:00","total":[{"playerID":"280310304","name":"Dody Herman","score":2442,"position":1},{"playerID":"276716748","name":"Jhoni Delvi","score":2159,"position":2},{"playerID":"290636693","name":"Diki","score":1910,"position":3},{"playerID":"193485499","name":"Gustriana","score":1646,"position":4},{"playerID":"292665631","name":"Sugih Ugih","score":64,"position":5}],"rank":{"2016-39":[{"playerID":"280310304","name":"Dody Herman","score":1201,"position":1},{"playerID":"276716748","name":"Jhoni Delvi","score":1054,"position":2},{"playerID":"290636693","name":"Diki","score":955,"position":3},{"playerID":"193485499","name":"Gustriana","score":823,"position":4},{"playerID":"292665631","name":"Sugih Ugih","score":32,"position":5}],"2016-40":[{"playerID":"280310304","name":"Dody Herman","score":1241,"position":1},{"playerID":"276716748","name":"Jhoni Delvi","score":1105,"position":2},{"playerID":"290636693","name":"Diki","score":955,"position":3},{"playerID":"193485499","name":"Gustriana","score":823,"position":4},{"playerID":"292665631","name":"Sugih Ugih","score":32,"position":5}]}}
