{"chanID":"-118997546","lastUpdated":"2016-09-06T05:00:19+02:00","total":[{"playerID":"215473437","name":"Bulan Tresna","score":26598,"position":1},{"playerID":"241371175","name":"Ratih Kartika Septiningtyas","score":15927,"position":2},{"playerID":"163195474","name":"- Eddy -","score":13414,"position":3},{"playerID":"54353782","name":"Alvin","score":9586,"position":4},{"playerID":"253556939","name":"Nur Indah","score":8368,"position":5},{"playerID":"260054033","name":"Gita Oktaviani","score":4565,"position":6},{"playerID":"194455277","name":"Gusti Satria Putra","score":3530,"position":7},{"playerID":"107142547","name":"Omar","score":3372,"position":8},{"playerID":"264248449","name":"Non Aida","score":1003,"position":9},{"playerID":"110067421","name":"Omar S","score":784,"position":10},{"playerID":"251812194","name":"Vinny Renyta","score":569,"position":11},{"playerID":"268096607","name":"Rudi Ganteng Katanya","score":426,"position":12},{"playerID":"238915578","name":"Putri Ayu","score":42,"position":13}],"rank":{"2016-28":[{"playerID":"194455277","name":"Gusti Satria Putra","score":288,"position":1},{"playerID":"215473437","name":"Bulan Tresna","score":233,"position":2},{"playerID":"110067421","name":"Omar S","score":47,"position":3}],"2016-29":[{"playerID":"215473437","name":"Bulan Tresna","score":4182,"position":1},{"playerID":"241371175","name":"Ratih Kartika Septiningtyas","score":2819,"position":2},{"playerID":"194455277","name":"Gusti Satria Putra","score":1529,"position":3},{"playerID":"264248449","name":"Non Aida","score":981,"position":4},{"playerID":"110067421","name":"Omar S","score":737,"position":5},{"playerID":"107142547","name":"Omar","score":467,"position":6},{"playerID":"251812194","name":"Vinny Renyta","score":359,"position":7}],"2016-30":[{"playerID":"215473437","name":"Bulan Tresna","score":3686,"position":1},{"playerID":"241371175","name":"Ratih Kartika Septiningtyas","score":2440,"position":2},{"playerID":"260054033","name":"Gita Oktaviani","score":2021,"position":3},{"playerID":"107142547","name":"Omar","score":1136,"position":4},{"playerID":"253556939","name":"Nur Indah","score":688,"position":5},{"playerID":"194455277","name":"Gusti Satria Putra","score":301,"position":6},{"playerID":"251812194","name":"Vinny Renyta","score":105,"position":7},{"playerID":"264248449","name":"Non Aida","score":11,"position":8}],"2016-31":[{"playerID":"215473437","name":"Bulan Tresna","score":4909,"position":1},{"playerID":"241371175","name":"Ratih Kartika Septiningtyas","score":3514,"position":2},{"playerID":"260054033","name":"Gita Oktaviani","score":2480,"position":3},{"playerID":"107142547","name":"Omar","score":1157,"position":4},{"playerID":"253556939","name":"Nur Indah","score":1052,"position":5},{"playerID":"194455277","name":"Gusti Satria Putra","score":637,"position":6},{"playerID":"251812194","name":"Vinny Renyta","score":105,"position":7},{"playerID":"264248449","name":"Non Aida","score":11,"position":8}],"2016-32":[{"playerID":"215473437","name":"Bulan Tresna","score":852,"position":1},{"playerID":"241371175","name":"Ratih Kartika Septiningtyas","score":563,"position":2},{"playerID":"253556939","name":"Nur Indah","score":453,"position":3},{"playerID":"194455277","name":"Gusti Satria Putra","score":251,"position":4},{"playerID":"260054033","name":"Gita Oktaviani","score":64,"position":5},{"playerID":"107142547","name":"Omar","score":24,"position":6}],"2016-33":[{"playerID":"215473437","name":"Bulan Tresna","score":987,"position":1},{"playerID":"253556939","name":"Nur Indah","score":979,"position":2},{"playerID":"241371175","name":"Ratih Kartika Septiningtyas","score":741,"position":3},{"playerID":"54353782","name":"Alvin","score":296,"position":4},{"playerID":"107142547","name":"Omar","score":133,"position":5}],"2016-34":[{"playerID":"215473437","name":"Bulan Tresna","score":3708,"position":1},{"playerID":"54353782","name":"Alvin","score":3202,"position":2},{"playerID":"253556939","name":"Nur Indah","score":2993,"position":3},{"playerID":"163195474","name":"- Eddy -","score":2657,"position":4},{"playerID":"241371175","name":"Ratih Kartika Septiningtyas","score":2130,"position":5},{"playerID":"107142547","name":"Omar","score":455,"position":6},{"playerID":"194455277","name":"Gusti Satria Putra","score":291,"position":7}],"2016-35":[{"playerID":"163195474","name":"- Eddy -","score":5162,"position":1},{"playerID":"215473437","name":"Bulan Tresna","score":3978,"position":2},{"playerID":"54353782","name":"Alvin","score":3044,"position":3},{"playerID":"241371175","name":"Ratih Kartika Septiningtyas","score":1860,"position":4},{"playerID":"253556939","name":"Nur Indah","score":1024,"position":5},{"playerID":"268096607","name":"Rudi Ganteng Katanya","score":213,"position":6},{"playerID":"238915578","name":"Putri Ayu","score":21,"position":7}],"2016-36":[{"playerID":"163195474","name":"- Eddy -","score":5595,"position":1},{"playerID":"215473437","name":"Bulan Tresna","score":4063,"position":2},{"playerID":"54353782","name":"Alvin","score":3044,"position":3},{"playerID":"241371175","name":"Ratih Kartika Septiningtyas","score":1860,"position":4},{"playerID":"253556939","name":"Nur Indah","score":1179,"position":5},{"playerID":"194455277","name":"Gusti Satria Putra","score":233,"position":6},{"playerID":"268096607","name":"Rudi Ganteng Katanya","score":213,"position":7},{"playerID":"238915578","name":"Putri Ayu","score":21,"position":8}]}}
