{"chanID":"-119667198","lastUpdated":"2016-08-08T07:35:22+02:00","total":[{"playerID":"129321386","name":"Darmink 38","score":2910,"position":1},{"playerID":"70907033","name":"Fian_Pappi 29 🇮🇩🔫","score":2032,"position":2},{"playerID":"96784159","name":"Asian Sihombing","score":1845,"position":3},{"playerID":"68261555","name":"Dzul Qadri","score":1473,"position":4},{"playerID":"157031604","name":"dody LND","score":1230,"position":5},{"playerID":"122494541","name":"Dede J kurniawan","score":781,"position":6},{"playerID":"111397476","name":"Raka 32","score":771,"position":7}],"rank":{"2016-30":[{"playerID":"129321386","name":"Darmink 38","score":812,"position":1},{"playerID":"70907033","name":"Fian_Pappi 29 🇮🇩🔫","score":502,"position":2},{"playerID":"157031604","name":"dody LND","score":410,"position":3},{"playerID":"96784159","name":"Asian Sihombing","score":391,"position":4},{"playerID":"68261555","name":"Dzul Qadri","score":327,"position":5},{"playerID":"111397476","name":"Raka 32","score":257,"position":6},{"playerID":"122494541","name":"Dede J kurniawan","score":195,"position":7}],"2016-31":[{"playerID":"129321386","name":"Darmink 38","score":1049,"position":1},{"playerID":"70907033","name":"Fian_Pappi 29 🇮🇩🔫","score":765,"position":2},{"playerID":"96784159","name":"Asian Sihombing","score":727,"position":3},{"playerID":"68261555","name":"Dzul Qadri","score":573,"position":4},{"playerID":"157031604","name":"dody LND","score":410,"position":5},{"playerID":"122494541","name":"Dede J kurniawan","score":293,"position":6},{"playerID":"111397476","name":"Raka 32","score":257,"position":7}],"2016-32":[{"playerID":"129321386","name":"Darmink 38","score":1049,"position":1},{"playerID":"70907033","name":"Fian_Pappi 29 🇮🇩🔫","score":765,"position":2},{"playerID":"96784159","name":"Asian Sihombing","score":727,"position":3},{"playerID":"68261555","name":"Dzul Qadri","score":573,"position":4},{"playerID":"157031604","name":"dody LND","score":410,"position":5},{"playerID":"122494541","name":"Dede J kurniawan","score":293,"position":6},{"playerID":"111397476","name":"Raka 32","score":257,"position":7}]}}
