{"chanID":"-121351810","lastUpdated":"2016-10-01T05:03:10+02:00","total":[{"playerID":"201643310","name":"Sharon Cabrian","score":1095,"position":1},{"playerID":"207035763","name":"Fernando Ferry","score":836,"position":2},{"playerID":"248045660","name":"Diko Ramelan","score":806,"position":3},{"playerID":"240632597","name":"Olivia C","score":365,"position":4},{"playerID":"243068280","name":"Dendy Yang","score":346,"position":5},{"playerID":"242772011","name":"Bernardus Bagus","score":98,"position":6}],"rank":{"2016-35":[{"playerID":"201643310","name":"Sharon Cabrian","score":506,"position":1},{"playerID":"207035763","name":"Fernando Ferry","score":418,"position":2},{"playerID":"248045660","name":"Diko Ramelan","score":403,"position":3},{"playerID":"243068280","name":"Dendy Yang","score":169,"position":4},{"playerID":"240632597","name":"Olivia C","score":157,"position":5},{"playerID":"242772011","name":"Bernardus Bagus","score":49,"position":6}],"2016-36":[{"playerID":"201643310","name":"Sharon Cabrian","score":506,"position":1},{"playerID":"207035763","name":"Fernando Ferry","score":418,"position":2},{"playerID":"248045660","name":"Diko Ramelan","score":403,"position":3},{"playerID":"243068280","name":"Dendy Yang","score":169,"position":4},{"playerID":"240632597","name":"Olivia C","score":157,"position":5},{"playerID":"242772011","name":"Bernardus Bagus","score":49,"position":6}],"2016-39":[{"playerID":"201643310","name":"Sharon Cabrian","score":83,"position":1},{"playerID":"240632597","name":"Olivia C","score":51,"position":2},{"playerID":"243068280","name":"Dendy Yang","score":8,"position":3}]}}
