{"chanID":"-121462099","lastUpdated":"2016-07-30T05:00:09+02:00","total":[{"playerID":"102754539","name":"Sony fals","score":10087,"position":1},{"playerID":"128774797","name":"Dani Kusumawati","score":9310,"position":2},{"playerID":"91990148","name":"Sofyan S","score":8094,"position":3},{"playerID":"84626447","name":"Indra Mellafiear","score":7421,"position":4},{"playerID":"129713117","name":"SUTRISNO 94152529","score":5314,"position":5},{"playerID":"222748815","name":"Aa Dzakiy","score":3148,"position":6},{"playerID":"103873908","name":"Kopi Oplet Jgl","score":2472,"position":7},{"playerID":"85249971","name":"Alex Satria","score":2227,"position":8},{"playerID":"72564581","name":"@rief","score":1533,"position":9},{"playerID":"73292407","name":"Khaerudin Heru","score":1513,"position":10},{"playerID":"107489742","name":"Agus Marwoto","score":1230,"position":11},{"playerID":"208684046","name":"Mustar","score":657,"position":12},{"playerID":"71554283","name":"TARMIJI","score":265,"position":13},{"playerID":"103173235","name":"Kopi Oplet Jgl","score":219,"position":14},{"playerID":"98579656","name":"Atoyyy","score":186,"position":15},{"playerID":"99319288","name":"koesja","score":84,"position":16}],"rank":{"2016-28":[{"playerID":"128774797","name":"Dani Kusumawati","score":3849,"position":1},{"playerID":"102754539","name":"Sony fals","score":3024,"position":2},{"playerID":"91990148","name":"Sofyan S","score":2950,"position":3},{"playerID":"222748815","name":"Aa Dzakiy","score":1574,"position":4},{"playerID":"129713117","name":"SUTRISNO 94152529","score":1151,"position":5},{"playerID":"84626447","name":"Indra Mellafiear","score":908,"position":6},{"playerID":"72564581","name":"@rief","score":670,"position":7},{"playerID":"85249971","name":"Alex Satria","score":629,"position":8},{"playerID":"107489742","name":"Agus Marwoto","score":615,"position":9},{"playerID":"73292407","name":"Khaerudin Heru","score":469,"position":10},{"playerID":"103873908","name":"Kopi Oplet Jgl","score":400,"position":11},{"playerID":"208684046","name":"Mustar","score":258,"position":12},{"playerID":"98579656","name":"Atoyyy","score":70,"position":13},{"playerID":"99319288","name":"koesja","score":42,"position":14}],"2016-29":[{"playerID":"102754539","name":"Sony fals","score":6790,"position":1},{"playerID":"84626447","name":"Indra Mellafiear","score":5974,"position":2},{"playerID":"128774797","name":"Dani Kusumawati","score":5461,"position":3},{"playerID":"91990148","name":"Sofyan S","score":4786,"position":4},{"playerID":"129713117","name":"SUTRISNO 94152529","score":3487,"position":5},{"playerID":"103873908","name":"Kopi Oplet Jgl","score":2072,"position":6},{"playerID":"222748815","name":"Aa Dzakiy","score":1574,"position":7},{"playerID":"85249971","name":"Alex Satria","score":1328,"position":8},{"playerID":"73292407","name":"Khaerudin Heru","score":899,"position":9},{"playerID":"72564581","name":"@rief","score":863,"position":10},{"playerID":"107489742","name":"Agus Marwoto","score":615,"position":11},{"playerID":"208684046","name":"Mustar","score":399,"position":12},{"playerID":"98579656","name":"Atoyyy","score":116,"position":13},{"playerID":"99319288","name":"koesja","score":42,"position":14}],"2016-30":[{"playerID":"129713117","name":"SUTRISNO 94152529","score":676,"position":1},{"playerID":"84626447","name":"Indra Mellafiear","score":539,"position":2},{"playerID":"91990148","name":"Sofyan S","score":358,"position":3},{"playerID":"102754539","name":"Sony fals","score":273,"position":4},{"playerID":"85249971","name":"Alex Satria","score":270,"position":5},{"playerID":"71554283","name":"TARMIJI","score":265,"position":6},{"playerID":"103173235","name":"Kopi Oplet Jgl","score":219,"position":7},{"playerID":"73292407","name":"Khaerudin Heru","score":145,"position":8}]}}
