{"chanID":"-125533855","lastUpdated":"2016-08-27T05:00:22+02:00","total":[{"playerID":"174656509","name":"Nova Yanti","score":2040,"position":1},{"playerID":"243874617","name":"Arfi Andini","score":2021,"position":2},{"playerID":"225577305","name":"Yenny Marsella","score":1951,"position":3},{"playerID":"244323400","name":"Ineke Wibowo","score":978,"position":4},{"playerID":"198974428","name":"Raras Warasantiningsih","score":815,"position":5},{"playerID":"235983421","name":"Valda Yunia","score":330,"position":6},{"playerID":"191619283","name":"Wildha Tampubolon","score":110,"position":7}],"rank":{"2016-32":[{"playerID":"243874617","name":"Arfi Andini","score":1947,"position":1},{"playerID":"174656509","name":"Nova Yanti","score":1928,"position":2},{"playerID":"225577305","name":"Yenny Marsella","score":1441,"position":3},{"playerID":"244323400","name":"Ineke Wibowo","score":846,"position":4},{"playerID":"198974428","name":"Raras Warasantiningsih","score":769,"position":5},{"playerID":"235983421","name":"Valda Yunia","score":330,"position":6},{"playerID":"191619283","name":"Wildha Tampubolon","score":110,"position":7}],"2016-33":[{"playerID":"225577305","name":"Yenny Marsella","score":255,"position":1},{"playerID":"244323400","name":"Ineke Wibowo","score":66,"position":2},{"playerID":"174656509","name":"Nova Yanti","score":56,"position":3},{"playerID":"243874617","name":"Arfi Andini","score":37,"position":4},{"playerID":"198974428","name":"Raras Warasantiningsih","score":23,"position":5}],"2016-34":[{"playerID":"225577305","name":"Yenny Marsella","score":255,"position":1},{"playerID":"244323400","name":"Ineke Wibowo","score":66,"position":2},{"playerID":"174656509","name":"Nova Yanti","score":56,"position":3},{"playerID":"243874617","name":"Arfi Andini","score":37,"position":4},{"playerID":"198974428","name":"Raras Warasantiningsih","score":23,"position":5}]}}
