{"chanID":"-134132125","lastUpdated":"2016-07-11T00:32:46+02:00","total":[{"playerID":"193868768","name":"Wirdha Salsabila","score":1123,"position":1},{"playerID":"248409121","name":"Rahmadani Yanti","score":562,"position":2},{"playerID":"223578670","name":"Hoiriyah Putri Septiani","score":423,"position":3},{"playerID":"262401014","name":"Vira Rahmadhani","score":401,"position":4}],"rank":{"2016-27":[{"playerID":"193868768","name":"Wirdha Salsabila","score":1123,"position":1},{"playerID":"248409121","name":"Rahmadani Yanti","score":562,"position":2},{"playerID":"223578670","name":"Hoiriyah Putri Septiani","score":423,"position":3},{"playerID":"262401014","name":"Vira Rahmadhani","score":401,"position":4}]}}
