{"chanID":"-136082501","lastUpdated":"2016-08-03T05:00:12+02:00","total":[{"playerID":"113231031","name":"Agra Bhasworo","score":943,"position":1},{"playerID":"169410193","name":"Mahendra","score":696,"position":2},{"playerID":"249119729","name":"Intan Yuwantika","score":420,"position":3},{"playerID":"217124894","name":"Priska","score":388,"position":4},{"playerID":"213915409","name":"Hashfi Hazazi","score":2,"position":5}],"rank":{"2016-31":[{"playerID":"113231031","name":"Agra Bhasworo","score":943,"position":1},{"playerID":"169410193","name":"Mahendra","score":696,"position":2},{"playerID":"249119729","name":"Intan Yuwantika","score":420,"position":3},{"playerID":"217124894","name":"Priska","score":388,"position":4},{"playerID":"213915409","name":"Hashfi Hazazi","score":2,"position":5}]}}
