{"chanID":"-140996816","lastUpdated":"2016-07-26T05:00:12+02:00","total":[{"playerID":"214372924","name":"Claudea Chintya","score":371,"position":1},{"playerID":"232593055","name":"Hendry Winata","score":354,"position":2},{"playerID":"264008157","name":"Meilita Chintya","score":309,"position":3},{"playerID":"262986699","name":"Welli Adi","score":217,"position":4},{"playerID":"207701060","name":"Shintia Yau","score":115,"position":5},{"playerID":"222834117","name":"Weldi Adi Pramana","score":31,"position":6}],"rank":{"2016-30":[{"playerID":"214372924","name":"Claudea Chintya","score":371,"position":1},{"playerID":"232593055","name":"Hendry Winata","score":354,"position":2},{"playerID":"264008157","name":"Meilita Chintya","score":309,"position":3},{"playerID":"262986699","name":"Welli Adi","score":217,"position":4},{"playerID":"207701060","name":"Shintia Yau","score":115,"position":5},{"playerID":"222834117","name":"Weldi Adi Pramana","score":31,"position":6}]}}
