{"chanID":"-143056339","lastUpdated":"2016-07-22T05:00:09+02:00","total":[{"playerID":"252100757","name":"Albizzia Haura","score":3913,"position":1},{"playerID":"168679228","name":"Hadana Siwanggi","score":3136,"position":2},{"playerID":"235933587","name":"Wan Natasya","score":2539,"position":3},{"playerID":"213401856","name":"Tazkia Suhaila","score":1322,"position":4},{"playerID":"250297918","name":"Teuku Meurah Fahmi","score":1209,"position":5},{"playerID":"135816268","name":"Cut Vicky Mauliana","score":438,"position":6},{"playerID":"246452766","name":"Mulyani Safira","score":258,"position":7},{"playerID":"189867889","name":"Siti Annisa","score":143,"position":8},{"playerID":"232800218","name":"Cut Tisa Humaira","score":36,"position":9}],"rank":{"2016-28":[{"playerID":"168679228","name":"Hadana Siwanggi","score":1357,"position":1},{"playerID":"252100757","name":"Albizzia Haura","score":1235,"position":2},{"playerID":"235933587","name":"Wan Natasya","score":889,"position":3},{"playerID":"213401856","name":"Tazkia Suhaila","score":642,"position":4},{"playerID":"135816268","name":"Cut Vicky Mauliana","score":219,"position":5},{"playerID":"250297918","name":"Teuku Meurah Fahmi","score":54,"position":6},{"playerID":"232800218","name":"Cut Tisa Humaira","score":18,"position":7}],"2016-29":[{"playerID":"252100757","name":"Albizzia Haura","score":2678,"position":1},{"playerID":"168679228","name":"Hadana Siwanggi","score":1779,"position":2},{"playerID":"235933587","name":"Wan Natasya","score":1650,"position":3},{"playerID":"250297918","name":"Teuku Meurah Fahmi","score":1155,"position":4},{"playerID":"213401856","name":"Tazkia Suhaila","score":680,"position":5},{"playerID":"246452766","name":"Mulyani Safira","score":258,"position":6},{"playerID":"135816268","name":"Cut Vicky Mauliana","score":219,"position":7},{"playerID":"189867889","name":"Siti Annisa","score":143,"position":8},{"playerID":"232800218","name":"Cut Tisa Humaira","score":18,"position":9}]}}
