{"chanID":"-146270888","lastUpdated":"2016-11-06T05:00:38+01:00","total":[{"playerID":"279872154","name":"Christine Irawan","score":181,"position":1},{"playerID":"262335392","name":"Felita Nathania","score":94,"position":2},{"playerID":"245742141","name":"Raka Darmayo","score":25,"position":3},{"playerID":"282982093","name":"Linda Gosan","score":0,"position":4}],"rank":{"2016-44":[{"playerID":"279872154","name":"Christine Irawan","score":181,"position":1},{"playerID":"262335392","name":"Felita Nathania","score":94,"position":2},{"playerID":"245742141","name":"Raka Darmayo","score":25,"position":3}]}}
