{"chanID":"-147823421","lastUpdated":"2016-08-04T05:00:08+02:00","total":[{"playerID":"243360383","name":"Dian Haf","score":216,"position":1},{"playerID":"237602243","name":"Angraeni Wiwi","score":208,"position":2},{"playerID":"257308601","name":"Fam100 Bot","score":182,"position":3},{"playerID":"242747557","name":"D I L A","score":142,"position":4}],"rank":{"2016-30":[{"playerID":"243360383","name":"Dian Haf","score":108,"position":1},{"playerID":"237602243","name":"Angraeni Wiwi","score":104,"position":2},{"playerID":"257308601","name":"Fam100 Bot","score":91,"position":3},{"playerID":"242747557","name":"D I L A","score":71,"position":4}],"2016-31":[{"playerID":"243360383","name":"Dian Haf","score":108,"position":1},{"playerID":"237602243","name":"Angraeni Wiwi","score":104,"position":2},{"playerID":"257308601","name":"Fam100 Bot","score":91,"position":3},{"playerID":"242747557","name":"D I L A","score":71,"position":4}]}}
