{"chanID":"-150359976","lastUpdated":"2016-11-06T05:00:38+01:00","total":[{"playerID":"284160712","name":"Dwita Hussy","score":572,"position":1},{"playerID":"244955104","name":"Fanny Febimillinesia","score":10,"position":2},{"playerID":"279304855","name":"Denissa","score":4,"position":3}],"rank":{"2016-43":[{"playerID":"284160712","name":"Dwita Hussy","score":286,"position":1},{"playerID":"244955104","name":"Fanny Febimillinesia","score":5,"position":2},{"playerID":"279304855","name":"Denissa","score":2,"position":3}],"2016-44":[{"playerID":"284160712","name":"Dwita Hussy","score":286,"position":1},{"playerID":"244955104","name":"Fanny Febimillinesia","score":5,"position":2},{"playerID":"279304855","name":"Denissa","score":2,"position":3}]}}
