{"chanID":"-150982087","lastUpdated":"2016-08-14T23:55:06+02:00","total":[{"playerID":"252221152","name":"Ayu Arauna","score":430,"position":1},{"playerID":"263954377","name":"Lia Maula","score":384,"position":2},{"playerID":"229765888","name":"Azhar R Mada N","score":234,"position":3},{"playerID":"253579080","name":"Dianira Pradnya Murti","score":210,"position":4},{"playerID":"183633589","name":"Rahmad Ariyantoro","score":103,"position":5},{"playerID":"73446216","name":"Robby Rakhmad Wahyudi","score":82,"position":6},{"playerID":"250481765","name":"Rezeika Handy Adrienufa","score":79,"position":7},{"playerID":"187990256","name":"Riky Mahardhika","score":66,"position":8}],"rank":{"2016-32":[{"playerID":"252221152","name":"Ayu Arauna","score":430,"position":1},{"playerID":"263954377","name":"Lia Maula","score":384,"position":2},{"playerID":"229765888","name":"Azhar R Mada N","score":234,"position":3},{"playerID":"253579080","name":"Dianira Pradnya Murti","score":210,"position":4},{"playerID":"183633589","name":"Rahmad Ariyantoro","score":103,"position":5},{"playerID":"73446216","name":"Robby Rakhmad Wahyudi","score":82,"position":6},{"playerID":"250481765","name":"Rezeika Handy Adrienufa","score":79,"position":7},{"playerID":"187990256","name":"Riky Mahardhika","score":66,"position":8}]}}
