{"chanID":"-150201971","lastUpdated":"2016-09-08T05:00:21+02:00","total":[{"playerID":"240510765","name":"Albert Cen","score":460,"position":1},{"playerID":"242786282","name":"yola amanda","score":406,"position":2},{"playerID":"269905689","name":"Winnie Avily","score":270,"position":3},{"playerID":"268064153","name":"Liliani Liloy","score":192,"position":4}],"rank":{"2016-35":[{"playerID":"240510765","name":"Albert Cen","score":230,"position":1},{"playerID":"242786282","name":"yola amanda","score":203,"position":2},{"playerID":"269905689","name":"Winnie Avily","score":135,"position":3},{"playerID":"268064153","name":"Liliani Liloy","score":96,"position":4}],"2016-36":[{"playerID":"240510765","name":"Albert Cen","score":230,"position":1},{"playerID":"242786282","name":"yola amanda","score":203,"position":2},{"playerID":"269905689","name":"Winnie Avily","score":135,"position":3},{"playerID":"268064153","name":"Liliani Liloy","score":96,"position":4}]}}
