{"chanID":"-152505376","lastUpdated":"2016-08-28T23:55:15+02:00","total":[{"playerID":"254414371","name":"Rizka Nathania","score":127,"position":1},{"playerID":"264512011","name":"Errin Erica","score":116,"position":2},{"playerID":"257329935","name":"Giovani Anggasta","score":83,"position":3},{"playerID":"227807892","name":"Chr Tjhw","score":70,"position":4}],"rank":{"2016-34":[{"playerID":"254414371","name":"Rizka Nathania","score":127,"position":1},{"playerID":"264512011","name":"Errin Erica","score":116,"position":2},{"playerID":"257329935","name":"Giovani Anggasta","score":83,"position":3},{"playerID":"227807892","name":"Chr Tjhw","score":70,"position":4}]}}
