{"chanID":"-153032925","lastUpdated":"2016-08-14T23:55:06+02:00","total":[{"playerID":"257966981","name":"Albert Setijo","score":365,"position":1},{"playerID":"241762119","name":"Sheryl","score":342,"position":2},{"playerID":"105232517","name":"Victor Pratama","score":307,"position":3}],"rank":{"2016-32":[{"playerID":"257966981","name":"Albert Setijo","score":365,"position":1},{"playerID":"241762119","name":"Sheryl","score":342,"position":2},{"playerID":"105232517","name":"Victor Pratama","score":307,"position":3}]}}
