{"chanID":"-155355124","lastUpdated":"2016-10-08T05:03:18+02:00","total":[{"playerID":"247827978","name":"Livinia Widi","score":394,"position":1},{"playerID":"243157778","name":"Tiffany Tomasina","score":139,"position":2},{"playerID":"224959483","name":"Selvy Widjaja","score":29,"position":3}],"rank":{"2016-40":[{"playerID":"247827978","name":"Livinia Widi","score":394,"position":1},{"playerID":"243157778","name":"Tiffany Tomasina","score":139,"position":2},{"playerID":"224959483","name":"Selvy Widjaja","score":29,"position":3}]}}
