{"chanID":"-155353554","lastUpdated":"2016-08-23T05:00:54+02:00","total":[{"playerID":"106783134","name":"Adinda Wungo","score":1134,"position":1},{"playerID":"201134212","name":"Stefanus Ho","score":718,"position":2},{"playerID":"257287861","name":"Sally Wirawan","score":452,"position":3}],"rank":{"2016-33":[{"playerID":"106783134","name":"Adinda Wungo","score":567,"position":1},{"playerID":"201134212","name":"Stefanus Ho","score":359,"position":2},{"playerID":"257287861","name":"Sally Wirawan","score":226,"position":3}],"2016-34":[{"playerID":"106783134","name":"Adinda Wungo","score":567,"position":1},{"playerID":"201134212","name":"Stefanus Ho","score":359,"position":2},{"playerID":"257287861","name":"Sally Wirawan","score":226,"position":3}]}}
