{"chanID":"-158978220","lastUpdated":"2016-10-09T05:00:34+02:00","total":[{"playerID":"220609443","name":"Tatang Murdio","score":3160,"position":1},{"playerID":"291596402","name":"ジャバル","score":1884,"position":2},{"playerID":"244213128","name":"Nia","score":1660,"position":3},{"playerID":"245539621","name":"Fitria","score":1008,"position":4},{"playerID":"272173482","name":"Enji Drive","score":814,"position":5},{"playerID":"268539970","name":"Tiara Anggie","score":724,"position":6},{"playerID":"274632973","name":"Indri","score":676,"position":7},{"playerID":"259958555","name":"Muthia Maharani","score":358,"position":8},{"playerID":"235127901","name":"Om Nanda","score":272,"position":9},{"playerID":"282998655","name":"Raafi Hamzah","score":198,"position":10},{"playerID":"251583854","name":"Millenia Mufta","score":134,"position":11},{"playerID":"260021381","name":"Ahmad Faiz Hafizhuddin","score":92,"position":12},{"playerID":"271642567","name":"Irwan","score":84,"position":13}],"rank":{"2016-39":[{"playerID":"220609443","name":"Tatang Murdio","score":1580,"position":1},{"playerID":"291596402","name":"Jabal El Thariq","score":942,"position":2},{"playerID":"244213128","name":"Nia","score":830,"position":3},{"playerID":"245539621","name":"Fitria","score":504,"position":4},{"playerID":"272173482","name":"Enji Drive","score":407,"position":5},{"playerID":"268539970","name":"Tiara Anggie","score":362,"position":6},{"playerID":"274632973","name":"Indri","score":338,"position":7},{"playerID":"259958555","name":"Muthia Maharani","score":179,"position":8},{"playerID":"235127901","name":"Om Nanda","score":136,"position":9},{"playerID":"282998655","name":"Raafi Hamzah","score":99,"position":10},{"playerID":"251583854","name":"Millenia Mufta","score":67,"position":11},{"playerID":"260021381","name":"Ahmad Faiz Hafizhuddin","score":46,"position":12},{"playerID":"271642567","name":"Irwan","score":42,"position":13}],"2016-40":[{"playerID":"220609443","name":"Tatang Murdio","score":1580,"position":1},{"playerID":"291596402","name":"ジャバル","score":942,"position":2},{"playerID":"244213128","name":"Nia","score":830,"position":3},{"playerID":"245539621","name":"Fitria","score":504,"position":4},{"playerID":"272173482","name":"Enji Drive","score":407,"position":5},{"playerID":"268539970","name":"Tiara Anggie","score":362,"position":6},{"playerID":"274632973","name":"Indri","score":338,"position":7},{"playerID":"259958555","name":"Muthia Maharani","score":179,"position":8},{"playerID":"235127901","name":"Om Nanda","score":136,"position":9},{"playerID":"282998655","name":"Raafi Hamzah","score":99,"position":10},{"playerID":"251583854","name":"Millenia Mufta","score":67,"position":11},{"playerID":"260021381","name":"Ahmad Faiz Hafizhuddin","score":46,"position":12},{"playerID":"271642567","name":"Irwan","score":42,"position":13}]}}
