{"chanID":"-161099787","lastUpdated":"2016-09-11T05:00:26+02:00","total":[{"playerID":"253720165","name":"ardhanata fauzan","score":555,"position":1},{"playerID":"221902260","name":"Gustiesar Albarry","score":433,"position":2},{"playerID":"211494210","name":"calvin wilson","score":272,"position":3},{"playerID":"261084189","name":"Tiara","score":186,"position":4},{"playerID":"240394803","name":"javier","score":65,"position":5},{"playerID":"194434467","name":"Almaash","score":28,"position":6}],"rank":{"2016-36":[{"playerID":"253720165","name":"ardhanata fauzan","score":555,"position":1},{"playerID":"221902260","name":"Gustiesar Albarry","score":433,"position":2},{"playerID":"211494210","name":"calvin wilson","score":272,"position":3},{"playerID":"261084189","name":"Tiara","score":186,"position":4},{"playerID":"240394803","name":"javier","score":65,"position":5},{"playerID":"194434467","name":"Almaash","score":28,"position":6}]}}
