{"chanID":"-163624229","lastUpdated":"2016-10-21T05:04:29+02:00","total":[{"playerID":"275431594","name":"Keyza Nyzky","score":712,"position":1},{"playerID":"210374484","name":"Rafdina Eka Putri","score":697,"position":2},{"playerID":"268571589","name":"Renata Thresza","score":584,"position":3},{"playerID":"239214524","name":"Babam Jo","score":366,"position":4},{"playerID":"244642793","name":"Daffa Abror","score":195,"position":5},{"playerID":"292602534","name":"Andina Aliffia M","score":195,"position":6},{"playerID":"269002483","name":"Hannyr Harun","score":37,"position":7}],"rank":{"2016-42":[{"playerID":"275431594","name":"Keyza Nyzky","score":712,"position":1},{"playerID":"210374484","name":"Rafdina Eka Putri","score":697,"position":2},{"playerID":"268571589","name":"Renata Thresza","score":584,"position":3},{"playerID":"239214524","name":"Babam Jo","score":366,"position":4},{"playerID":"292602534","name":"Andina Aliffia M","score":195,"position":5},{"playerID":"244642793","name":"Daffa Abror","score":195,"position":6},{"playerID":"269002483","name":"Hannyr Harun","score":37,"position":7}]}}
