{"chanID":"-163960299","lastUpdated":"2016-10-22T05:04:07+02:00","total":[{"playerID":"266712528","name":"Siti Amalia Ramadhaniyah","score":252,"position":1},{"playerID":"265171614","name":"Erindah","score":194,"position":2},{"playerID":"238779095","name":"Fatiah Chumairoh","score":159,"position":3},{"playerID":"220561761","name":"Silvana Anindya","score":32,"position":4}],"rank":{"2016-31":[{"playerID":"266712528","name":"Siti Amalia Ramadhaniyah","score":126,"position":1},{"playerID":"265171614","name":"Erindah","score":97,"position":2},{"playerID":"238779095","name":"Fatiah Chumairoh","score":62,"position":3}],"2016-32":[{"playerID":"266712528","name":"Siti Amalia Ramadhaniyah","score":126,"position":1},{"playerID":"265171614","name":"Erindah","score":97,"position":2},{"playerID":"238779095","name":"Fatiah Chumairoh","score":62,"position":3}],"2016-42":[{"playerID":"238779095","name":"Fatiah Chumairoh","score":35,"position":1},{"playerID":"220561761","name":"Silvana Anindya","score":32,"position":2}]}}
