{"chanID":"-163629539","lastUpdated":"2016-09-20T05:00:34+02:00","total":[{"playerID":"242718508","name":"Veronica Oktavia","score":830,"position":1},{"playerID":"255692159","name":"Argo Sambuaga","score":822,"position":2},{"playerID":"289293597","name":"Mika K","score":514,"position":3},{"playerID":"283959217","name":"Anesfa R","score":420,"position":4},{"playerID":"263299652","name":"sayang♡","score":328,"position":5}],"rank":{"2016-37":[{"playerID":"242718508","name":"Veronica Oktavia","score":415,"position":1},{"playerID":"255692159","name":"Argo Sambuaga","score":411,"position":2},{"playerID":"289293597","name":"Mika K","score":257,"position":3},{"playerID":"283959217","name":"Anesfa R","score":210,"position":4},{"playerID":"263299652","name":"sayang♡","score":164,"position":5}],"2016-38":[{"playerID":"242718508","name":"Veronica Oktavia","score":415,"position":1},{"playerID":"255692159","name":"Argo Sambuaga","score":411,"position":2},{"playerID":"289293597","name":"Mika K","score":257,"position":3},{"playerID":"283959217","name":"Anesfa R","score":210,"position":4},{"playerID":"263299652","name":"sayang♡","score":164,"position":5}]}}
