{"chanID":"-163634381","lastUpdated":"2016-09-11T23:55:16+02:00","total":[{"playerID":"189790688","name":"Imer","score":10178,"position":1},{"playerID":"225016334","name":"Johannes Romero","score":8309,"position":2},{"playerID":"278866655","name":"Maya Wahyuningtias","score":7952,"position":3},{"playerID":"267117769","name":"Andara Tisnadisastra","score":5269,"position":4},{"playerID":"165607719","name":"Farah Fauziah","score":3937,"position":5},{"playerID":"203771760","name":"Suzanna Silitonga","score":3271,"position":6},{"playerID":"289805608","name":"Daniel Aditya","score":3267,"position":7},{"playerID":"288401544","name":"Caroline Thadate","score":498,"position":8},{"playerID":"270396899","name":"Cikko Malik","score":475,"position":9}],"rank":{"2016-36":[{"playerID":"189790688","name":"Imer","score":10178,"position":1},{"playerID":"225016334","name":"Johannes Romero","score":8309,"position":2},{"playerID":"278866655","name":"Maya Wahyuningtias","score":7952,"position":3},{"playerID":"267117769","name":"Andara Tisnadisastra","score":5269,"position":4},{"playerID":"165607719","name":"Farah Fauziah","score":3937,"position":5},{"playerID":"203771760","name":"Suzanna Silitonga","score":3271,"position":6},{"playerID":"289805608","name":"Daniel Aditya","score":3267,"position":7},{"playerID":"288401544","name":"Caroline Thadate","score":498,"position":8},{"playerID":"270396899","name":"Cikko Malik","score":475,"position":9}]}}
