{"chanID":"-164391629","lastUpdated":"2016-08-25T05:00:40+02:00","total":[{"playerID":"215865017","name":"Maria 🌶","score":6507,"position":1},{"playerID":"252440982","name":"Della Pradecta","score":2195,"position":2},{"playerID":"250552281","name":"Gabriella Glady","score":2169,"position":3},{"playerID":"259338771","name":"Zakiy Azizah","score":1435,"position":4}],"rank":{"2016-33":[{"playerID":"215865017","name":"Maria 🌶","score":2860,"position":1},{"playerID":"252440982","name":"Della Pradecta","score":1054,"position":2},{"playerID":"250552281","name":"Gabriella Glady","score":857,"position":3},{"playerID":"259338771","name":"Zakiy Azizah","score":553,"position":4}],"2016-34":[{"playerID":"215865017","name":"Maria 🌶","score":3647,"position":1},{"playerID":"250552281","name":"Gabriella Glady","score":1312,"position":2},{"playerID":"252440982","name":"Della Pradecta","score":1141,"position":3},{"playerID":"259338771","name":"Zakiy Azizah","score":882,"position":4}]}}
