{"chanID":"-165129651","lastUpdated":"2016-07-31T05:00:09+02:00","total":[{"playerID":"214621048","name":"Carissa Ignacia","score":1226,"position":1},{"playerID":"154360548","name":"Freddyhan Suhargo","score":1118,"position":2},{"playerID":"267777426","name":"Alvin Wijaya","score":518,"position":3},{"playerID":"252011011","name":"Audrya P","score":263,"position":4},{"playerID":"263100785","name":"Hendro Yan","score":152,"position":5}],"rank":{"2016-30":[{"playerID":"214621048","name":"Carissa Ignacia","score":1226,"position":1},{"playerID":"154360548","name":"Freddyhan Suhargo","score":1118,"position":2},{"playerID":"267777426","name":"Alvin Wijaya","score":518,"position":3},{"playerID":"252011011","name":"Audrya P","score":263,"position":4},{"playerID":"263100785","name":"Hendro Yan","score":152,"position":5}]}}
