{"chanID":"-167510328","lastUpdated":"2016-09-22T05:01:13+02:00","total":[{"playerID":"163281848","name":"Ibnu Abrar","score":331,"position":1},{"playerID":"278607111","name":"Nur Indah Permata Sari","score":233,"position":2},{"playerID":"231786818","name":"annis","score":135,"position":3},{"playerID":"126350292","name":"Joshua","score":120,"position":4},{"playerID":"172428716","name":"Rifki Rachman","score":93,"position":5},{"playerID":"205200384","name":"Diah Dwi C","score":60,"position":6},{"playerID":"247456749","name":"Taufan Ali","score":38,"position":7}],"rank":{"2016-38":[{"playerID":"163281848","name":"Ibnu Abrar","score":331,"position":1},{"playerID":"278607111","name":"Nur Indah Permata Sari","score":233,"position":2},{"playerID":"231786818","name":"annis","score":135,"position":3},{"playerID":"126350292","name":"Joshua","score":120,"position":4},{"playerID":"172428716","name":"Rifki Rachman","score":93,"position":5},{"playerID":"205200384","name":"Diah Dwi C","score":60,"position":6},{"playerID":"247456749","name":"Taufan Ali","score":38,"position":7}]}}
