{"chanID":"-167240322","lastUpdated":"2016-08-23T05:00:54+02:00","total":[{"playerID":"189348711","name":"Azzahra Yasmine","score":70,"position":1},{"playerID":"254786047","name":"Metta Angela","score":52,"position":2},{"playerID":"222224207","name":"Najmin Khairani","score":46,"position":3},{"playerID":"255837454","name":"Shafa","score":43,"position":4},{"playerID":"178151467","name":"Virginia Natasya","score":41,"position":5}],"rank":{"2016-34":[{"playerID":"189348711","name":"Azzahra Yasmine","score":70,"position":1},{"playerID":"254786047","name":"Metta Angela","score":52,"position":2},{"playerID":"222224207","name":"Najmin Khairani","score":46,"position":3},{"playerID":"255837454","name":"Shafa","score":43,"position":4},{"playerID":"178151467","name":"Virginia Natasya","score":41,"position":5}]}}
