{"chanID":"-169794303","lastUpdated":"2016-09-30T05:02:08+02:00","total":[{"playerID":"270254467","name":"David Liemyanto","score":3041,"position":1},{"playerID":"226221306","name":"David Lievander","score":2544,"position":2},{"playerID":"293064551","name":"Steven Chandra","score":2016,"position":3},{"playerID":"209036353","name":"Junaidi Jayanto","score":1142,"position":4},{"playerID":"270591919","name":"Rudy Zavier","score":985,"position":5},{"playerID":"296691782","name":"Angelina Yully","score":824,"position":6},{"playerID":"136907435","name":"PK-59 Andre Tanzil","score":762,"position":7},{"playerID":"271091906","name":"Agnes Hiola","score":696,"position":8},{"playerID":"249004193","name":"Reyner Wijoyo","score":289,"position":9},{"playerID":"298376829","name":"Leonardo Tamin","score":278,"position":10},{"playerID":"212199359","name":"Catherina","score":249,"position":11},{"playerID":"277561158","name":"Windy Tanajaya","score":246,"position":12},{"playerID":"243220307","name":"steven ang","score":245,"position":13},{"playerID":"259234612","name":"Harry Ang","score":114,"position":14},{"playerID":"266146213","name":"Sheryl","score":105,"position":15},{"playerID":"280252862","name":"Topi Jerami","score":40,"position":16},{"playerID":"242740397","name":"lie sander","score":25,"position":17},{"playerID":"241698502","name":"Alecia Khorianto","score":14,"position":18},{"playerID":"253484025","name":"Devon Febrian Theixar","score":1,"position":19}],"rank":{"2016-38":[{"playerID":"270254467","name":"David Liemyanto","score":1111,"position":1},{"playerID":"293064551","name":"Steven Chandra","score":1004,"position":2},{"playerID":"296691782","name":"Angelina Yully","score":768,"position":3},{"playerID":"270591919","name":"Rudy Zavier","score":691,"position":4},{"playerID":"271091906","name":"Agnes Hiola","score":567,"position":5},{"playerID":"226221306","name":"David Lievander","score":415,"position":6},{"playerID":"209036353","name":"Junaidi Jayanto","score":412,"position":7},{"playerID":"136907435","name":"PK-59 Andre Tanzil","score":390,"position":8},{"playerID":"298376829","name":"Leonardo Tamin","score":223,"position":9},{"playerID":"277561158","name":"Windy Tanajaya","score":218,"position":10},{"playerID":"243220307","name":"steven ang","score":196,"position":11},{"playerID":"212199359","name":"Catherina","score":169,"position":12},{"playerID":"280252862","name":"Topi Jerami","score":40,"position":13}],"2016-39":[{"playerID":"226221306","name":"David Lievander","score":2129,"position":1},{"playerID":"270254467","name":"David Liemyanto","score":1930,"position":2},{"playerID":"293064551","name":"Steven Chandra","score":1012,"position":3},{"playerID":"209036353","name":"Junaidi Jayanto","score":730,"position":4},{"playerID":"136907435","name":"PK-59 Andre Tanzil","score":372,"position":5},{"playerID":"270591919","name":"Rudy Zavier","score":294,"position":6},{"playerID":"249004193","name":"Reyner Wijoyo","score":289,"position":7},{"playerID":"271091906","name":"Agnes Hiola","score":129,"position":8},{"playerID":"259234612","name":"Harry Ang","score":114,"position":9},{"playerID":"266146213","name":"Sheryl","score":105,"position":10},{"playerID":"212199359","name":"Catherina","score":80,"position":11},{"playerID":"296691782","name":"Angelina Yully","score":56,"position":12},{"playerID":"298376829","name":"Leonardo Tamin","score":55,"position":13},{"playerID":"243220307","name":"steven ang","score":49,"position":14},{"playerID":"277561158","name":"Windy Tanajaya","score":28,"position":15},{"playerID":"242740397","name":"lie sander","score":25,"position":16},{"playerID":"241698502","name":"Alecia Khorianto","score":14,"position":17},{"playerID":"253484025","name":"Devon Febrian Theixar","score":1,"position":18}]}}
