{"chanID":"-170511377","lastUpdated":"2016-08-14T23:55:06+02:00","total":[{"playerID":"177027163","name":"Kartika Vidya","score":3621,"position":1},{"playerID":"255633878","name":"Aprilliarie chiesa","score":3410,"position":2},{"playerID":"258121345","name":"naurah","score":2461,"position":3},{"playerID":"154611965","name":"Amira Islamey","score":2076,"position":4},{"playerID":"240378682","name":"Nia","score":1524,"position":5},{"playerID":"247367674","name":"Kharismaaa","score":1466,"position":6},{"playerID":"253818957","name":"amandanasha","score":993,"position":7},{"playerID":"245600860","name":"Dinda Hemalia","score":936,"position":8},{"playerID":"220086700","name":"Avila Asmawi","score":793,"position":9},{"playerID":"192745614","name":"Ichaa","score":591,"position":10},{"playerID":"264426921","name":"Qinthara Alfarisi","score":587,"position":11},{"playerID":"254576642","name":"Fauzan","score":478,"position":12},{"playerID":"230658620","name":"Ahmad N.A.","score":215,"position":13},{"playerID":"245024676","name":"Ikhlas Fathur","score":136,"position":14}],"rank":{"2016-31":[{"playerID":"177027163","name":"Kartika Vidya","score":939,"position":1},{"playerID":"154611965","name":"Amira Islamey","score":628,"position":2},{"playerID":"258121345","name":"naurah","score":384,"position":3}],"2016-32":[{"playerID":"255633878","name":"Aprilliarie chiesa","score":3410,"position":1},{"playerID":"177027163","name":"Kartika Vidya","score":2682,"position":2},{"playerID":"258121345","name":"naurah","score":2077,"position":3},{"playerID":"240378682","name":"Nia","score":1524,"position":4},{"playerID":"247367674","name":"Kharismaaa","score":1466,"position":5},{"playerID":"154611965","name":"Amira Islamey","score":1448,"position":6},{"playerID":"253818957","name":"amandanasha","score":993,"position":7},{"playerID":"245600860","name":"Dinda Hemalia","score":936,"position":8},{"playerID":"220086700","name":"Avila Asmawi","score":793,"position":9},{"playerID":"192745614","name":"Ichaa","score":591,"position":10},{"playerID":"264426921","name":"Qinthara Alfarisi","score":587,"position":11},{"playerID":"254576642","name":"Fauzan","score":478,"position":12},{"playerID":"230658620","name":"Ahmad N.A.","score":215,"position":13},{"playerID":"245024676","name":"Ikhlas Fathur","score":136,"position":14}]}}
