{"chanID":"-171604228","lastUpdated":"2016-10-15T05:02:46+02:00","total":[{"playerID":"195267388","name":"Natasha chan","score":5062,"position":1},{"playerID":"264065362","name":"Ayu Felisia","score":2006,"position":2},{"playerID":"294611183","name":"Hariz Yudha","score":1914,"position":3},{"playerID":"284675463","name":"Syarifah Annisa Fajriyah","score":1335,"position":4},{"playerID":"264568616","name":"Clara Mutia","score":1174,"position":5},{"playerID":"247556139","name":"Adesept","score":990,"position":6},{"playerID":"178192003","name":"ENG-IND Translator","score":789,"position":7},{"playerID":"287094731","name":"Ryan Aquario","score":673,"position":8},{"playerID":"260003566","name":"kikiokt","score":610,"position":9},{"playerID":"295701340","name":"Bayu Valerinoya","score":562,"position":10},{"playerID":"237313425","name":"dindy anggeriani","score":432,"position":11},{"playerID":"218651642","name":"Aldhy Ramanda","score":376,"position":12},{"playerID":"225757231","name":"Black Widow","score":343,"position":13},{"playerID":"285774134","name":"Hariz Yudha Lafran","score":265,"position":14},{"playerID":"277591557","name":"Muhammad Tri Wahyudi","score":253,"position":15},{"playerID":"283119138","name":"Boy Anak Jalanan","score":202,"position":16},{"playerID":"263116743","name":"Tolu Akbar","score":156,"position":17},{"playerID":"204410520","name":"Satrio Aji Pambudi","score":109,"position":18},{"playerID":"215378506","name":"Riko Septiawn","score":102,"position":19},{"playerID":"288253713","name":"Muhammad Komarul Hakim","score":40,"position":20},{"playerID":"194691280","name":"Rizqo Zuriattson","score":36,"position":21},{"playerID":"270472163","name":"Ade Septio","score":36,"position":22},{"playerID":"272177739","name":"Zilly D","score":30,"position":23},{"playerID":"256184168","name":"Danang Permadi","score":0,"position":24},{"playerID":"205926693","name":"Geovani Novita","score":0,"position":25},{"playerID":"261743566","name":"Cosman Oktaniel","score":0,"position":26}],"rank":{"2016-40":[{"playerID":"294611183","name":"Hariz Yudha","score":711,"position":1},{"playerID":"195267388","name":"Natasha chan","score":614,"position":2},{"playerID":"264568616","name":"Clara Mutia","score":295,"position":3},{"playerID":"247556139","name":"Adesept","score":263,"position":4},{"playerID":"295701340","name":"Bayu Valerinoya","score":51,"position":5},{"playerID":"218651642","name":"Aldhy Ramanda","score":50,"position":6}],"2016-41":[{"playerID":"195267388","name":"Natasha chan","score":4448,"position":1},{"playerID":"264065362","name":"Ayu Felisia","score":2006,"position":2},{"playerID":"284675463","name":"Syarifah Annisa Fajriyah","score":1335,"position":3},{"playerID":"294611183","name":"Hariz Yudha","score":1203,"position":4},{"playerID":"264568616","name":"Clara Mutia","score":879,"position":5},{"playerID":"178192003","name":"ENG-IND Translator","score":789,"position":6},{"playerID":"247556139","name":"Adesept","score":727,"position":7},{"playerID":"287094731","name":"Ryan Aquario","score":673,"position":8},{"playerID":"260003566","name":"kikiokt","score":610,"position":9},{"playerID":"295701340","name":"Bayu Valerinoya","score":511,"position":10},{"playerID":"237313425","name":"dindy anggeriani","score":432,"position":11},{"playerID":"225757231","name":"Black Widow","score":343,"position":12},{"playerID":"218651642","name":"Aldhy Ramanda","score":326,"position":13},{"playerID":"285774134","name":"Hariz Yudha Lafran","score":265,"position":14},{"playerID":"277591557","name":"Muhammad Tri Wahyudi","score":253,"position":15},{"playerID":"283119138","name":"Boy Anak Jalanan","score":202,"position":16},{"playerID":"263116743","name":"Tolu Akbar","score":156,"position":17},{"playerID":"204410520","name":"Satrio Aji Pambudi","score":109,"position":18},{"playerID":"215378506","name":"Riko Septiawn","score":102,"position":19},{"playerID":"288253713","name":"Muhammad Komarul Hakim","score":40,"position":20},{"playerID":"270472163","name":"Ade Septio","score":36,"position":21},{"playerID":"194691280","name":"Rizqo Zuriattson","score":36,"position":22},{"playerID":"272177739","name":"Zilly D","score":30,"position":23}]}}
