{"chanID":"-173271269","lastUpdated":"2016-08-20T05:00:14+02:00","total":[{"playerID":"118148173","name":"Melissa Imbang","score":5896,"position":1},{"playerID":"117461272","name":"Aldino Faraday","score":2341,"position":2},{"playerID":"173851910","name":"Ricky Berlianto","score":2332,"position":3},{"playerID":"71602326","name":"Andrew Imbang","score":2275,"position":4},{"playerID":"191843175","name":"Aldi Farad Simpati","score":2140,"position":5},{"playerID":"152424566","name":"Amanda Putri","score":1262,"position":6},{"playerID":"237913342","name":"Renny Modok","score":788,"position":7},{"playerID":"240637350","name":"Adam Imbang","score":314,"position":8},{"playerID":"181658461","name":"Petrick Modok","score":132,"position":9}],"rank":{"2016-31":[{"playerID":"118148173","name":"Melissa Imbang","score":2702,"position":1},{"playerID":"117461272","name":"Aldino Faraday","score":1908,"position":2},{"playerID":"71602326","name":"Andrew Imbang","score":1480,"position":3},{"playerID":"173851910","name":"Ricky Berlianto","score":781,"position":4}],"2016-32":[{"playerID":"118148173","name":"Melissa Imbang","score":3093,"position":1},{"playerID":"191843175","name":"Aldi Farad Simpati","score":2062,"position":2},{"playerID":"173851910","name":"Ricky Berlianto","score":1551,"position":3},{"playerID":"152424566","name":"Amanda Putri","score":1262,"position":4},{"playerID":"71602326","name":"Andrew Imbang","score":795,"position":5},{"playerID":"237913342","name":"Renny Modok","score":788,"position":6},{"playerID":"117461272","name":"Aldino Faraday","score":433,"position":7},{"playerID":"240637350","name":"Adam Imbang","score":314,"position":8},{"playerID":"181658461","name":"Petrick Modok","score":132,"position":9}],"2016-33":[{"playerID":"118148173","name":"Melissa Imbang","score":101,"position":1},{"playerID":"191843175","name":"Aldi Farad Simpati","score":78,"position":2}]}}
