{"chanID":"-175712088","lastUpdated":"2016-09-09T05:00:20+02:00","total":[{"playerID":"252116278","name":"Taufiq Prihantoro","score":70,"position":1},{"playerID":"273798357","name":"Mauas M. G.","score":50,"position":2},{"playerID":"229643199","name":"Kevin Hutama","score":45,"position":3},{"playerID":"272021101","name":"Selly Setiawati","score":40,"position":4}],"rank":{"2016-36":[{"playerID":"252116278","name":"Taufiq Prihantoro","score":70,"position":1},{"playerID":"273798357","name":"Mauas M. G.","score":50,"position":2},{"playerID":"229643199","name":"Kevin Hutama","score":45,"position":3},{"playerID":"272021101","name":"Selly Setiawati","score":40,"position":4}]}}
