{"chanID":"-175621664","lastUpdated":"2016-10-07T05:02:27+02:00","total":[{"playerID":"266176796","name":"Anindya Ramadhanti","score":200,"position":1},{"playerID":"287257171","name":"Ramadhan Kurniawan","score":145,"position":2},{"playerID":"280285204","name":"Dhia Hasna","score":78,"position":3},{"playerID":"269430144","name":"Anrialdo Pratama","score":68,"position":4},{"playerID":"275747253","name":"Tiara Muliannie","score":64,"position":5}],"rank":{"2016-40":[{"playerID":"266176796","name":"Anindya Ramadhanti","score":200,"position":1},{"playerID":"287257171","name":"Ramadhan Kurniawan","score":145,"position":2},{"playerID":"280285204","name":"Dhia Hasna","score":78,"position":3},{"playerID":"269430144","name":"Anrialdo Pratama","score":68,"position":4},{"playerID":"275747253","name":"Tiara Muliannie","score":64,"position":5}]}}
