{"chanID":"-175584553","lastUpdated":"2016-10-11T05:02:01+02:00","total":[{"playerID":"277763081","name":"Aryo Hafidzan","score":2017,"position":1},{"playerID":"292470082","name":"Rafli","score":437,"position":2},{"playerID":"249467234","name":"King Kylie","score":387,"position":3},{"playerID":"275589755","name":"Fachri Fahlevi","score":354,"position":4},{"playerID":"236223737","name":"Daffa Tp","score":351,"position":5},{"playerID":"298139421","name":"Orbi Yuanto","score":222,"position":6},{"playerID":"281898501","name":"Nazil Alfayed","score":144,"position":7}],"rank":{"2016-40":[{"playerID":"298139421","name":"Orbi Yuanto","score":222,"position":1},{"playerID":"277763081","name":"Aryo Hafidzan","score":129,"position":2},{"playerID":"236223737","name":"Daffa Tp","score":21,"position":3}],"2016-41":[{"playerID":"277763081","name":"Aryo Hafidzan","score":1888,"position":1},{"playerID":"292470082","name":"Rafli","score":437,"position":2},{"playerID":"249467234","name":"King Kylie","score":387,"position":3},{"playerID":"275589755","name":"Fachri Fahlevi","score":354,"position":4},{"playerID":"236223737","name":"Daffa Tp","score":330,"position":5},{"playerID":"281898501","name":"Nazil Alfayed","score":144,"position":6}]}}
