{"chanID":"-176177608","lastUpdated":"2016-10-23T23:55:26+02:00","total":[{"playerID":"281486759","name":"Muhammad Iqbal Elpasya","score":3754,"position":1},{"playerID":"238536359","name":"M Reza Pahlevi","score":3624,"position":2},{"playerID":"239938202","name":"Adriansyah Ahmad","score":991,"position":3},{"playerID":"239218973","name":"Àrif Toms","score":906,"position":4},{"playerID":"273896542","name":"Nike Astriani","score":801,"position":5},{"playerID":"292662839","name":"Frankenstein","score":609,"position":6},{"playerID":"284074336","name":"arifin ramadhan","score":279,"position":7}],"rank":{"2016-40":[{"playerID":"281486759","name":"Muhammad Iqbal Elpasya","score":3457,"position":1},{"playerID":"238536359","name":"M Reza Pahlevi","score":3405,"position":2},{"playerID":"239938202","name":"Adriansyah Ahmad","score":991,"position":3},{"playerID":"273896542","name":"Nike Astriani","score":801,"position":4},{"playerID":"239218973","name":"Àrif Toms","score":699,"position":5},{"playerID":"292662839","name":"Frankenstein","score":609,"position":6},{"playerID":"284074336","name":"arifin ramadhan","score":279,"position":7}],"2016-42":[{"playerID":"281486759","name":"Muhammad Iqbal Elpasya","score":297,"position":1},{"playerID":"238536359","name":"M Reza Pahlevi","score":219,"position":2},{"playerID":"239218973","name":"Àrif Toms","score":207,"position":3}]}}
