{"chanID":"-176663889","lastUpdated":"2016-10-08T05:03:18+02:00","total":[{"playerID":"221907775","name":"Ardeva Ranti","score":5904,"position":1},{"playerID":"183993315","name":"Mia K Heryan","score":5326,"position":2},{"playerID":"264621465","name":"Nilam Sitaresmi","score":3640,"position":3},{"playerID":"244659672","name":"Hikmah Azani","score":3344,"position":4},{"playerID":"262032800","name":"Arrya Anandika","score":1638,"position":5},{"playerID":"205825381","name":"Rozalia","score":712,"position":6},{"playerID":"238918492","name":"Arum Nabila","score":258,"position":7}],"rank":{"2016-33":[{"playerID":"244659672","name":"Hikmah Azani66","score":1354,"position":1},{"playerID":"221907775","name":"Ardeva Ranti","score":655,"position":2},{"playerID":"183993315","name":"Mia K Heryan","score":387,"position":3},{"playerID":"262032800","name":"Arrya Anandika","score":361,"position":4},{"playerID":"205825381","name":"Rozalia","score":346,"position":5},{"playerID":"238918492","name":"Arum Nabila","score":129,"position":6}],"2016-34":[{"playerID":"244659672","name":"Hikmah Azani66","score":1354,"position":1},{"playerID":"221907775","name":"Ardeva Ranti","score":655,"position":2},{"playerID":"183993315","name":"Mia K Heryan","score":387,"position":3},{"playerID":"262032800","name":"Arrya Anandika","score":361,"position":4},{"playerID":"205825381","name":"Rozalia","score":346,"position":5},{"playerID":"238918492","name":"Arum Nabila","score":129,"position":6}],"2016-35":[{"playerID":"221907775","name":"Ardeva Ranti","score":58,"position":1},{"playerID":"264621465","name":"Nilam Sitaresmi","score":56,"position":2},{"playerID":"262032800","name":"Arrya Anandika","score":41,"position":3}],"2016-36":[{"playerID":"221907775","name":"Ardeva Ranti","score":58,"position":1},{"playerID":"264621465","name":"Nilam Sitaresmi","score":56,"position":2},{"playerID":"262032800","name":"Arrya Anandika","score":41,"position":3}],"2016-39":[{"playerID":"183993315","name":"Mia K Heryan","score":2024,"position":1},{"playerID":"221907775","name":"Ardeva Ranti","score":1787,"position":2},{"playerID":"264621465","name":"Nilam Sitaresmi","score":1539,"position":3},{"playerID":"244659672","name":"Hikmah Azani","score":318,"position":4},{"playerID":"262032800","name":"Arrya Anandika","score":229,"position":5},{"playerID":"205825381","name":"Rozalia","score":10,"position":6}],"2016-40":[{"playerID":"221907775","name":"Ardeva Ranti","score":2691,"position":1},{"playerID":"183993315","name":"Mia K Heryan","score":2528,"position":2},{"playerID":"264621465","name":"Nilam Sitaresmi","score":1989,"position":3},{"playerID":"262032800","name":"Arrya Anandika","score":605,"position":4},{"playerID":"244659672","name":"Hikmah Azani","score":318,"position":5},{"playerID":"205825381","name":"Rozalia","score":10,"position":6}]}}
