{"chanID":"-178659087","lastUpdated":"2016-09-25T05:00:24+02:00","total":[{"playerID":"258156106","name":"Affandi Yusuf","score":1249,"position":1},{"playerID":"282741933","name":"putri salsabila","score":1082,"position":2},{"playerID":"262596307","name":"Dika Erlangga","score":959,"position":3},{"playerID":"238798859","name":"jabal harahap","score":506,"position":4}],"rank":{"2016-38":[{"playerID":"258156106","name":"Affandi Yusuf","score":1249,"position":1},{"playerID":"282741933","name":"putri salsabila","score":1082,"position":2},{"playerID":"262596307","name":"Dika Erlangga","score":959,"position":3},{"playerID":"238798859","name":"jabal harahap","score":506,"position":4}]}}
